{
  "main": {
    "id": "0b28f2d00383f889",
    "type": "split",
    "children": [
      {
        "id": "d3c3c19ab6ba2a1d",
        "type": "tabs",
        "children": [
          {
            "id": "896a33399805f0ca",
            "type": "leaf",
            "state": {
              "type": "markdown",
              "state": {
                "file": "02 MOC/MOC IT/MOC Programowanie obiektowe.md",
                "mode": "source",
                "source": false,
                "backlinks": true,
                "backlinkOpts": {
                  "collapseAll": false,
                  "extraContext": false,
                  "sortOrder": "alphabetical",
                  "showSearch": false,
                  "searchQuery": "",
                  "backlinkCollapsed": false,
                  "unlinkedCollapsed": true
                }
              },
              "icon": "lucide-file",
              "title": "MOC Programowanie obiektowe"
            }
          },
          {
            "id": "835f45659b596db9",
            "type": "leaf",
            "state": {
              "type": "markdown",
              "state": {
                "file": "03 Atomy/Programowanie obiektowe.md",
                "mode": "source",
                "source": false,
                "backlinks": true,
                "backlinkOpts": {
                  "collapseAll": false,
                  "extraContext": false,
                  "sortOrder": "alphabetical",
                  "showSearch": false,
                  "searchQuery": "",
                  "backlinkCollapsed": false,
                  "unlinkedCollapsed": true
                }
              },
              "icon": "lucide-file",
              "title": "Programowanie obiektowe"
            }
          },
          {
            "id": "c982da20faac4186",
            "type": "leaf",
            "state": {
              "type": "markdown",
              "state": {
                "file": "03 Atomy/C Sharp.md",
                "mode": "source",
                "source": false,
                "backlinks": true,
                "backlinkOpts": {
                  "collapseAll": false,
                  "extraContext": false,
                  "sortOrder": "alphabetical",
                  "showSearch": false,
                  "searchQuery": "",
                  "backlinkCollapsed": false,
                  "unlinkedCollapsed": true
                }
              },
              "icon": "lucide-file",
              "title": "C Sharp"
            }
          },
          {
            "id": "1a3b4761f78859cf",
            "type": "leaf",
            "state": {
              "type": "markdown",
              "state": {
                "file": "03 Atomy/Sterta (pamięć).md",
                "mode": "source",
                "source": false,
                "backlinks": true,
                "backlinkOpts": {
                  "collapseAll": false,
                  "extraContext": false,
                  "sortOrder": "alphabetical",
                  "showSearch": false,
                  "searchQuery": "",
                  "backlinkCollapsed": false,
                  "unlinkedCollapsed": true
                }
              },
              "icon": "lucide-file",
              "title": "Sterta (pamięć)"
            }
          },
          {
            "id": "18c91bdae9e7e292",
            "type": "leaf",
            "state": {
              "type": "markdown",
              "state": {
                "file": "03 Atomy/Stos (pamięć).md",
                "mode": "source",
                "source": false,
                "backlinks": true,
                "backlinkOpts": {
                  "collapseAll": false,
                  "extraContext": false,
                  "sortOrder": "alphabetical",
                  "showSearch": false,
                  "searchQuery": "",
                  "backlinkCollapsed": false,
                  "unlinkedCollapsed": true
                }
              },
              "icon": "lucide-file",
              "title": "Stos (pamięć)"
            }
          }
        ],
        "currentTab": 4
      }
    ],
    "direction": "vertical"
  },
  "left": {
    "id": "e466418690912808",
    "type": "split",
    "children": [
      {
        "id": "afa0241213312a77",
        "type": "tabs",
        "children": [
          {
            "id": "180c24419c3d71cd",
            "type": "leaf",
            "state": {
              "type": "file-explorer",
              "state": {
                "sortOrder": "alphabetical",
                "autoReveal": false
              },
              "icon": "lucide-folder-closed",
              "title": "Przeglądarka plików"
            }
          },
          {
            "id": "5f3082bf1e46927d",
            "type": "leaf",
            "state": {
              "type": "search",
              "state": {
                "query": "",
                "matchingCase": false,
                "explainSearch": false,
                "collapseAll": true,
                "extraContext": false,
                "sortOrder": "alphabetical"
              },
              "icon": "lucide-search",
              "title": "Wyszukiwarka"
            }
          },
          {
            "id": "69d01e453fd632ec",
            "type": "leaf",
            "state": {
              "type": "bookmarks",
              "state": {},
              "icon": "lucide-bookmark",
              "title": "Zakładki"
            }
          }
        ]
      }
    ],
    "direction": "horizontal",
    "width": 310.5
  },
  "right": {
    "id": "a85f4e0e20d537cf",
    "type": "split",
    "children": [
      {
        "id": "3ceb2b4b38599e44",
        "type": "tabs",
        "dimension": 64.48275862068965,
        "children": [
          {
            "id": "e1893cc11c72edd3",
            "type": "leaf",
            "state": {
              "type": "markdown",
              "state": {
                "file": "Skróty klawiszowe.md",
                "mode": "source",
                "source": false,
                "backlinks": true,
                "backlinkOpts": {
                  "collapseAll": false,
                  "extraContext": false,
                  "sortOrder": "alphabetical",
                  "showSearch": false,
                  "searchQuery": "",
                  "backlinkCollapsed": false,
                  "unlinkedCollapsed": true
                }
              },
              "icon": "lucide-file",
              "title": "Skróty klawiszowe"
            }
          },
          {
            "id": "920fedb2dc89a41b",
            "type": "leaf",
            "state": {
              "type": "backlink",
              "state": {
                "file": "03 Atomy/Typy Całkowitoliczbowe w C Sharp.md",
                "collapseAll": true,
                "extraContext": true,
                "sortOrder": "alphabetical",
                "showSearch": false,
                "searchQuery": "",
                "backlinkCollapsed": false,
                "unlinkedCollapsed": true
              },
              "icon": "links-coming-in",
              "title": "Linki zwrotne do Typy Całkowitoliczbowe w C Sharp"
            }
          },
          {
            "id": "8f0a7c164af1f281",
            "type": "leaf",
            "state": {
              "type": "outgoing-link",
              "state": {
                "file": "03 Atomy/Typy Całkowitoliczbowe w C Sharp.md",
                "linksCollapsed": false,
                "unlinkedCollapsed": true
              },
              "icon": "links-going-out",
              "title": "Łącza wychodzące z Typy Całkowitoliczbowe w C Sharp"
            }
          },
          {
            "id": "35d17179836c30f8",
            "type": "leaf",
            "state": {
              "type": "tag",
              "state": {
                "sortOrder": "frequency",
                "useHierarchy": true,
                "showSearch": false,
                "searchQuery": ""
              },
              "icon": "lucide-tags",
              "title": "Tagi"
            }
          },
          {
            "id": "07133ca3d150880e",
            "type": "leaf",
            "state": {
              "type": "outline",
              "state": {
                "file": "03 Atomy/Programowanie generyczne.md",
                "followCursor": true,
                "showSearch": false,
                "searchQuery": ""
              },
              "icon": "lucide-list",
              "title": "Konspekt Programowanie generyczne"
            }
          },
          {
            "id": "614b3d579e2cc010",
            "type": "leaf",
            "state": {
              "type": "advanced-tables-toolbar",
              "state": {},
              "icon": "lucide-ghost",
              "title": "advanced-tables-toolbar"
            }
          },
          {
            "id": "94dc124f54ace88f",
            "type": "leaf",
            "state": {
              "type": "all-properties",
              "state": {
                "sortOrder": "frequency",
                "showSearch": false,
                "searchQuery": ""
              },
              "icon": "lucide-archive",
              "title": "Wszystkie atrybuty"
            }
          }
        ]
      },
      {
        "id": "175e8c35941872f1",
        "type": "tabs",
        "dimension": 35.51724137931034,
        "children": [
          {
            "id": "f345f2db3cd24e5c",
            "type": "leaf",
            "state": {
              "type": "graph",
              "state": {},
              "icon": "lucide-git-fork",
              "title": "Podgląd grafu"
            }
          }
        ]
      }
    ],
    "direction": "horizontal",
    "width": 200
  },
  "left-ribbon": {
    "hiddenItems": {
      "obsidian-git:Open Git source control": false,
      "obsidian-bible-reference:Bible Verse Lookup": false,
      "obisidian-note-linker:Note Linker": false,
      "edit-history:Open edit history": false,
      "templater-obsidian:Templater": false,
      "obsidian-kanban:Create new board": false,
      "canvas:Stwórz nową tablicę": false,
      "templates:Wstaw szablon": false,
      "graph:Otwórz podgląd grafu": false,
      "daily-notes:Otwórz dzisiejszy dziennik": false,
      "switcher:Otwórz okno szybkiego wyboru": false,
      "command-palette:Otwórz listę poleceń": false,
      "bases:Stwórz nową bazę danych": false,
      "table-editor-obsidian:Advanced Tables Toolbar": false
    }
  },
  "active": "18c91bdae9e7e292",
  "lastOpenFiles": [
    "01 Input przejściowy/IT⌨️/Struktury danych/Stos (struktura danych).md",
    "03 Atomy/Stos (pamięć).md",
    "03 Atomy/Sterta (pamięć).md",
    "03 Atomy/Alokacja obiektu na stosie i stercie.md",
    "03 Atomy/Konstruktor.md",
    "03 Atomy/Konstruktor.md.edtz",
    "02 MOC/MOC IT/MOC Programowanie obiektowe.md",
    "03 Atomy/Programowanie obiektowe.md",
    "03 Atomy/C Sharp.md",
    "Skróty klawiszowe.md",
    "03 Atomy/Alokacja obiektu na stosie i stercie.md.edtz",
    "03 Atomy/Polimorfizm (programowanie).md",
    "03 Atomy/Metoda statyczna vs instancyjna.md",
    "03 Atomy/Hermetyzacja.md",
    "03 Atomy/Typy danych w C Sharp.md",
    "02 MOC/MOC IT/MOC Typy danych.md",
    "03 Atomy/Tekstowy typ danych.md",
    "03 Atomy/Całkowitoliczbowy typ danych.md",
    "03 Atomy/Koncepcja – Typ danych.md",
    "Gotowanie/Gnocchi z cukinią i marchewką.md",
    "Gotowanie/Gnocchi z cukinią i marchewką.md.edtz",
    "Gotowanie/Pieczone gnocchi z warzywami, tofu i sosem musztardowo-jogurtowym.md",
    "Gotowanie/Brokuł stir fry curry.md",
    "Gotowanie/Brokuł stir fry curry.md.edtz",
    "Gotowanie/Pieczone gnocchi z warzywami, tofu i sosem musztardowo-jogurtowym.md.edtz",
    "03 Atomy/Polimorfizm (programowanie).md.edtz",
    "03 Atomy/Dziedziczenie (programowanie).md",
    "03 Atomy/Enkapsulacja.md",
    "03 Atomy/Enkapuslacja.md",
    "03 Atomy/Dziedziczenie (programowanie).md.edtz",
    "03 Atomy/Klasa (programowanie).md",
    "Gotowanie/Surówka z buraka.md",
    "Gotowanie/Pieczony kalafior Orzo.md",
    "Gotowanie/Surówka z buraka.md.edtz",
    "03 Atomy/Hermetyzacja.md.edtz",
    "03 Atomy/Enkapuslacja.md.edtz",
    "03 Atomy/załączniki/Bramka XNOR.webp",
    "03 Atomy/załączniki/Bramka XOR.webp",
    "03 Atomy/załączniki/Bramka NOR2.webp",
    "03 Atomy/załączniki/Bramka NOR.webp",
    "03 Atomy/załączniki/Bramka NAND2.webp",
    "03 Atomy/załączniki/Bramka NAND.webp",
    "03 Atomy/załączniki/Bramka NOT.webp",
    "03 Atomy/załączniki/Bramka OR.webp",
    "03 Atomy/załączniki/Bramka AND.webp",
    "03 Atomy/załączniki/Transmisja równoległa.webp"
  ]
}